Workbook

Sheet Company-Info
B1: Company Name | C1: Company Code | D1: Cap Category | E1: Sector | F1: Business Focus | G1: NSE Symbol | H1: BSE Code | I1: Listing | J1: Financials Used
B2: Infosys Ltd | C2: INFY | D2: Large Cap | E2: IT Services | F2: Global IT & Consulting | G2: INFY | H2: 500209 | I2: NSE & BSE | J2: Consolidated
B3: Coforge Ltd | C3: COFORGE | D3: Mid Cap | E3: IT Services | F3: Digital Services | G3: COFORGE | H3: 532927 | I3: NSE & BSE | J3: Consolidated
B4: Dynacons Systems & Solutions Ltd | C4: DSSL | D4: Small Cap | E4: IT Services | F4: System Integration | G4: DSSL | H4: 532365 | I4: NSE & BSE | J4: Consolidated

Sheet Finance_Indicators
A1: Company Code | B1: Fiscal Year | C1: Revenue (in ₹ crore) | D1: Net Profit (in ₹ crore) | E1: Operating Expenses (in ₹ crore) | F1: Operating Profit (in ₹ crore) | G1: EPS(Basic) (in ₹)
A2: INFY | B2: 2025 | C2: 162990 | D2: 26713 | E2: 128566 | F2: =$C2-$E2 -> 34424 | G2: 64.5
A3: INFY | B3: 2024 | C3: 153670 | D3: 26233 | E3: 121923 | F3: =$C3-$E3 -> 31747 | G3: 63.39
A4: INFY | B4: 2023 | C4: 146767 | D4: 24095 | E4: 115862 | F4: =$C4-$E4 -> 30905 | G4: 57.63
A5: INFY | B5: 2022 | C5: 121641 | D5: 22110 | E5: 93626 | F5: =$C5-$E5 -> 28015 | G5: 52.52
A6: INFY | B6: 2021 | C6: 100472 | D6: 19351 | E6: 75850 | F6: =$C6-$E6 -> 24622 | G6: 45.61
A7: COFORGE | B7: 2025 | C7: 12050.7 | D7: 932.6 | E7: 10784.6 | F7: =$C7-$E7 -> 1266.1 | G7: 127.16
A8: COFORGE | B8: 2024 | C8: 9179 | D8: 835.6 | E8: 8069.9 | F8: =$C8-$E8 -> 1109.1 | G8: 133.73
A9: COFORGE | B9: 2023 | C9: 8014.6 | D9: 745.1 | E9: 6956.4 | F9: =$C9-$E9 -> 1058.2 | G9: 113.77
A10: COFORGE | B10: 2022 | C10: 6432 | D10: 714.7 | E10: 5557.3 | F10: =$C10-$E10 -> 874.7 | G10: 109.02
A11: COFORGE | B11: 2021 | C11: 4662.8 | D11: 466 | E11: 4066.9 | F11: =$C11-$E11 -> 595.9 | G11: 74.68
A12: DSSL | B12: 2025 | C12: 1273.93 | D12: 72.49 | E12: 1163.57 | F12: =$C12-$E12 -> 110.36 | G12: 57.01
A13: DSSL | B13: 2024 | C13: 1028.85 | D13: 53.81 | E13: 947.99 | F13: =$C13-$E13 -> 80.86 | G13: 42.41
... A16: DSSL | B16: 2021 | C16: 437.25 | D16: 8.54 | E16: 418.74 | F16: =$C16-$E16 -> 18.51 | G16: 9.33

Sheet Ratios
A1: Company Code | B1: Fiscal Year | C1: Operating Profit Margin (in %) | D1: Net Profit Margin (in %) | E1: ROE (in %) | F1: ROCE (in %) | G1: P/E (times)
A2: INFY | B2: 2025 | C2: =Finance_Indicators!F2/Finance_Indicators!C2*100 -> 21.120314 | D2: =Finance_Indicators!D2/Finance_Indicators!C2*100 -> 16.389349 | E2: 29 | F2: 33.6 | G2: 24.4
A3: INFY | B3: 2024 | C3: =Finance_Indicators!F3/Finance_Indicators!C3*100 -> 20.659205 | D3: =Finance_Indicators!D3/Finance_Indicators!C3*100 -> 17.070996 | E3: 32.1 | F3: 34.2 | G3: 23.6
A4: INFY | B4: 2023 | C4: =Finance_Indicators!F4/Finance_Indicators!C4*100 -> 21.057186 | D4: =Finance_Indicators!D4/Finance_Indicators!C4*100 -> 16.417178 | E4: 31.2 | F4: 36.2 | G4: 24.8
A5: INFY | B5: 2022 | C5: =Finance_Indicators!F5/Finance_Indicators!C5*100 -> 23.030886 | D5: =Finance_Indicators!D5/Finance_Indicators!C5*100 -> 18.176437 | E5: 29.1 | F5: 33.2 | G5: 36.3
A6: INFY | B6: 2021 | C6: =Finance_Indicators!F6/Finance_Indicators!C6*100 -> 24.50633 | D6: =Finance_Indicators!D6/Finance_Indicators!C6*100 -> 19.260092 | E6: 27.4 | F6: 36.5 | G6: 30
A7: COFORGE | B7: 2025 | C7: =Finance_Indicators!F7/Finance_Indicators!C7*100 -> 10.506444 | D7: =Finance_Indicators!D7/Finance_Indicators!C7*100 -> 7.7389695 | E7: 17.7 | F7: 17.7 | G7: 12.7
A8: COFORGE | B8: 2024 | C8: =Finance_Indicators!F8/Finance_Indicators!C8*100 -> 12.083016 | D8: =Finance_Indicators!D8/Finance_Indicators!C8*100 -> 9.1033882 | E8: 24 | F8: 24 | G8: 8.2
A9: COFORGE | B9: 2023 | C9: =Finance_Indicators!F9/Finance_Indicators!C9*100 -> 13.203404 | D9: =Finance_Indicators!D9/Finance_Indicators!C9*100 -> 9.2967834 | E9: 27.4 | F9: 27.4 | G9: 6.7
A10: COFORGE | B10: 2022 | C10: =Finance_Indicators!F10/Finance_Indicators!C10*100 -> 13.599192 | D10: =Finance_Indicators!D10/Finance_Indicators!C10*100 -> 11.111629 | E10: 27.1 | F10: 27.1 | G10: 8.2
A11: COFORGE | B11: 2021 | C11: =Finance_Indicators!F11/Finance_Indicators!C11*100 -> 12.779875 | D11: =Finance_Indicators!D11/Finance_Indicators!C11*100 -> 9.993995 | E11: 22.4 | F11: 22.4 | G11: 7.8
A12: DSSL | B12: 2025 | C12: =Finance_Indicators!F12/Finance_Indicators!C12*100 -> 8.6629564 | D12: =Finance_Indicators!D12/Finance_Indicators!C12*100 -> 5.6902656 | E12: 37.31 | F12: 38.9 | G12: 18.1
A13: DSSL | B13: 2024 | C13: =Finance_Indicators!F13/Finance_Indicators!C13*100 -> 7.8592603 | D13: =Finance_Indicators!D13/Finance_Indicators!C13*100 -> 5.2301113 | E13: 41.02 | F13: 38.19 | G13: 24.2
... A16: DSSL | B16: 2021 | C16: =Finance_Indicators!F16/Finance_Indicators!C16*100 -> 4.2332762 | D16: =Finance_Indicators!D16/Finance_Indicators!C16*100 -> 1.9531161 | E16: 19.71 | F16: 21.78 | G16: 8

Sheet Index_Calculations
A1: Company Code | B1: Fiscal Year | C1: Revenue (in ₹ crore) | D1: Net Profit (in ₹ crore) | E1: Index Revenue (in ₹ crore) | F1: Index Net Profit (in ₹ crore)
A2: INFY | B2: 2025 | C2: 162990 | D2: 26713 | E2: =(C2/$C$6)*100 -> 162.2243 | F2: =(D2/$D$6)*100 -> 138.04455
A3: INFY | B3: 2024 | C3: 153670 | D3: 26233 | E3: =(C3/$C$6)*100 -> 152.94809 | F3: =(D3/$D$6)*100 -> 135.56405
A4: INFY | B4: 2023 | C4: 146767 | D4: 24095 | E4: =(C4/$C$6)*100 -> 146.07751 | F4: =(D4/$D$6)*100 -> 124.51553
A5: INFY | B5: 2022 | C5: 121641 | D5: 22110 | E5: =(C5/$C$6)*100 -> 121.06955 | F5: =(D5/$D$6)*100 -> 114.25766
A6: INFY | B6: 2021 | C6: 100472 | D6: 19351 | E6: =(C6/$C$6)*100 -> 100 | F6: =(D6/$D$6)*100 -> 100
A7: COFORGE | B7: 2025 | C7: 12050.7 | D7: 932.6 | E7: =(C7/$C$11)*100 -> 258.44342 | F7: =(D7/$D$11)*100 -> 200.12876
A8: COFORGE | B8: 2024 | C8: 9179 | D8: 835.6 | E8: =(C8/$C$11)*100 -> 196.85597 | F8: =(D8/$D$11)*100 -> 179.3133
A9: COFORGE | B9: 2023 | C9: 8014.6 | D9: 745.1 | E9: =(C9/$C$11)*100 -> 171.88385 | F9: =(D9/$D$11)*100 -> 159.8927
A10: COFORGE | B10: 2022 | C10: 6432 | D10: 714.7 | E10: =(C10/$C$11)*100 -> 137.94287 | F10: =(D10/$D$11)*100 -> 153.3691
A11: COFORGE | B11: 2021 | C11: 4662.8 | D11: 466 | E11: =(C11/$C$11)*100 -> 100 | F11: =(D11/$D$11)*100 -> 100
A12: DSSL | B12: 2025 | C12: 1273.93 | D12: 72.49 | E12: =(C12/$C$16)*100 -> 291.35049 | F12: =(D12/$D$16)*100 -> 848.82904
A13: DSSL | B13: 2024 | C13: 1028.85 | D13: 53.81 | E13: =(C13/$C$16)*100 -> 235.30017 | F13: =(D13/$D$16)*100 -> 630.09368
A14: DSSL | B14: 2023 | C14: 806.77 | D14: 33.45 | E14: =(C14/$C$16)*100 -> 184.51001 | F14: =(D14/$D$16)*100 -> 391.68618
A15: DSSL | B15: 2022 | C15: 655.84 | D15: 16.43 | E15: =(C15/$C$16)*100 -> 149.992 | F15: =(D15/$D$16)*100 -> 192.38876
A16: DSSL | B16: 2021 | C16: 437.25 | D16: 8.54 | E16: =(C16/$C$16)*100 -> 100 | F16: =(D16/$D$16)*100 -> 100

Sheet Scale&Growth

Sheet INDEXED_SCALE&GROWTH

Sheet Efficiency&Returns
